rest_framework_serializer_field_permissions/__init__.py
rest_framework_serializer_field_permissions/fields.py
rest_framework_serializer_field_permissions/permissions.py
rest_framework_serializer_field_permissions/serializers.py
django_rest_serializer_field_permissions-4.0.0.dist-info/LICENSE
django_rest_serializer_field_permissions-4.0.0.dist-info/METADATA
django_rest_serializer_field_permissions-4.0.0.dist-info/WHEEL
django_rest_serializer_field_permissions-4.0.0.dist-info/top_level.txt
django_rest_serializer_field_permissions-4.0.0.dist-info/RECORD
