Metadata-Version: 2.1
Name: django-rest-serializer-field-permissions
Version: 4.0.0
Summary: Field-by-field serializer permissions for Django Rest Framework.
Home-page: https://github.com/InterSIS/django-rest-serializer-field-permissions/
Author: The Intersis Foundation
Author-email: dev@intersis.org
License: GNU General Public License v3 (GPLv3)
Platform: UNKNOWN
Classifier: Environment :: Web Environment
Classifier: Framework :: Django
Classifier: Intended Audience :: Developers
Classifier: License :: OSI Approved :: GNU General Public License v3 (GPLv3)
Classifier: Operating System :: OS Independent
Classifier: Programming Language :: Python
Classifier: Programming Language :: Python :: 3.7
Classifier: Topic :: Internet :: WWW/HTTP
Classifier: Topic :: Internet :: WWW/HTTP :: Dynamic Content
Requires-Dist: django (>=2.1)
Requires-Dist: djangorestframework (~=3.0)
